UJOSchema/__init__.py
UJOSchema/__main__.py
UJOSchema/constraints.py
UJOSchema/parser.py
UJOSchema/ranges.py
UJOSchema/schema.py
UJOSchema/transformer.py
UJOSchema/utils.py
UJOSchema/converter/__init__.py
UJOSchema/converter/base.py
UJOSchema/converter/binary.py
UJOSchema/converter/json.py
UJOSchema/converter/markdown.py
UJOSchema/converter/ujotypes.py
UJOSchema/grammar/terminals.lark
UJOSchema/grammar/ujs.lark
UJOSchema/grammar/ujs_types.lark
UJOSchema/types/__init__.py
UJOSchema/types/basic.py
UJOSchema/types/container.py
UJOSchema/types/object.py
UJOSchema/types/record.py
UJOSchema/types/typedef.py
UJOSchema-0.4.83.data/data/LICENSE
test/__init__.py
UJOSchema-0.4.83.dist-info/LICENSE
UJOSchema-0.4.83.dist-info/METADATA
UJOSchema-0.4.83.dist-info/WHEEL
UJOSchema-0.4.83.dist-info/top_level.txt
UJOSchema-0.4.83.dist-info/RECORD
