Metadata-Version: 2.1
Name: UJOSchema
Version: 0.4.83
Summary: UJO Schema is an easy to read and easyto write language to define UJO data structures
Home-page: https://www.industrial-devops.org
Author: Maik Wojcieszak
Author-email: mw@wobew-systems.com
License: MIT
Classifier: License :: OSI Approved :: MIT License
Classifier: Operating System :: OS Independent
Classifier: Development Status :: 4 - Beta
Classifier: Programming Language :: Python :: 3 :: Only
Classifier: Programming Language :: Python :: 3.7
Classifier: Programming Language :: Python :: 3.8
Classifier: Programming Language :: Python :: 3.9
Classifier: Programming Language :: Python :: 3.10
Classifier: Programming Language :: Python :: 3.11
Classifier: Programming Language :: Python :: 3.12
License-File: LICENSE
Requires-Dist: lark-parser
Requires-Dist: docopt
Requires-Dist: ujotypes
